twodo/cli.py
twodo-1.2.dist-info/METADATA
twodo-1.2.dist-info/WHEEL
twodo-1.2.dist-info/entry_points.txt
twodo-1.2.dist-info/top_level.txt
twodo-1.2.dist-info/RECORD
