Metadata-Version: 2.1
Name: twodo
Version: 1.2
Summary: Yet another simple todo cli in Python
Home-page: https://github.com/realamirali/2do
Author: Amirali Esfandiari
Author-email: amiralinull@gmail.com
License: UNKNOWN
Platform: UNKNOWN
Classifier: License :: OSI Approved :: MIT License
Requires-Python: >=3
Requires-Dist: fire
